shennong/cli.py
shennong/py.typed
shennong-0.0.0.dist-info/METADATA
shennong-0.0.0.dist-info/WHEEL
shennong-0.0.0.dist-info/RECORD
