Metadata-Version: 2.4
Name: shennong
Version: 0.0.0
Summary: Placholder for futur use
License-Expression: MIT
Requires-Python: <4.0,>=3.12
Classifier: Programming Language :: Python :: 3
Classifier: Programming Language :: Python :: 3.12
Classifier: Programming Language :: Python :: 3.13
Classifier: Programming Language :: Python :: 3.14
